<?xml version='1.0' encoding='UTF-8'?>
<package version="1.0.0" uuid="yoshimotomotion-efa3ec">
 <names>
  <name lang="en_US">YoshimotoMotion</name>
 </names>
 <supportedLanguages>
  <language>en_US</language>
 </supportedLanguages>
 <descriptionLanguages>
  <language>en_US</language>
 </descriptionLanguages>
 <contents>
  <behaviorContent path="ネガティブ/-_あきれ">
   <nature>interactive</nature>
   <permissions/>
  </behaviorContent>
  <behaviorContent path="ネガティブ/-_あり得ない">
   <nature>interactive</nature>
   <permissions/>
  </behaviorContent>
  <behaviorContent path="ネガティブ/-_いやいや">
   <nature>interactive</nature>
   <permissions/>
  </behaviorContent>
  <behaviorContent path="ネガティブ/-_え！？">
   <nature>interactive</nature>
   <permissions/>
  </behaviorContent>
  <behaviorContent path="ネガティブ/-_それはない%20">
   <nature>interactive</nature>
   <permissions/>
  </behaviorContent>
  <behaviorContent path="ネガティブ/-_だめだこりゃ">
   <nature>interactive</nature>
   <permissions/>
  </behaviorContent>
  <behaviorContent path="ネガティブ/-_やれやれ">
   <nature>interactive</nature>
   <permissions/>
  </behaviorContent>
  <behaviorContent path="ネガティブ/-_わかったわかった">
   <nature>interactive</nature>
   <permissions/>
  </behaviorContent>
  <behaviorContent path="ネガティブ/-_キャー">
   <nature>interactive</nature>
   <permissions/>
  </behaviorContent>
  <behaviorContent path="ネガティブ/-_ドンマイ">
   <nature>interactive</nature>
   <permissions/>
  </behaviorContent>
  <behaviorContent path="ネガティブ/-_下向き">
   <nature>interactive</nature>
   <permissions/>
  </behaviorContent>
  <behaviorContent path="ネガティブ/-_伏し目">
   <nature>interactive</nature>
   <permissions/>
  </behaviorContent>
  <behaviorContent path="ネガティブ/-_恥ずかし">
   <nature>interactive</nature>
   <permissions/>
  </behaviorContent>
  <behaviorContent path="ネガティブ/-_普通じゃん">
   <nature>interactive</nature>
   <permissions/>
  </behaviorContent>
  <behaviorContent path="ネガティブ/-_照れ">
   <nature>interactive</nature>
   <permissions/>
  </behaviorContent>
  <behaviorContent path="ネガティブ/-_絶対無理">
   <nature>interactive</nature>
   <permissions/>
  </behaviorContent>
  <behaviorContent path="ネガティブ/-_頭かきかき">
   <nature>interactive</nature>
   <permissions/>
  </behaviorContent>
  <behaviorContent path="ネガティブ/-_首横にふる">
   <nature>interactive</nature>
   <permissions/>
  </behaviorContent>
  <behaviorContent path="ノーマル/n_あせってフリック">
   <nature>interactive</nature>
   <permissions/>
  </behaviorContent>
  <behaviorContent path="ノーマル/n_いいですか？">
   <nature>interactive</nature>
   <permissions/>
  </behaviorContent>
  <behaviorContent path="ノーマル/n_うなずき">
   <nature>interactive</nature>
   <permissions/>
  </behaviorContent>
  <behaviorContent path="ノーマル/n_お辞儀">
   <nature>interactive</nature>
   <permissions/>
  </behaviorContent>
  <behaviorContent path="ノーマル/n_がっかり">
   <nature>interactive</nature>
   <permissions/>
  </behaviorContent>
  <behaviorContent path="ノーマル/n_これです">
   <nature>interactive</nature>
   <permissions/>
  </behaviorContent>
  <behaviorContent path="ノーマル/n_どうです皆さん">
   <nature>interactive</nature>
   <permissions/>
  </behaviorContent>
  <behaviorContent path="ノーマル/n_もっとがっかり">
   <nature>interactive</nature>
   <permissions/>
  </behaviorContent>
  <behaviorContent path="ノーマル/n_やや右！">
   <nature>interactive</nature>
   <permissions/>
  </behaviorContent>
  <behaviorContent path="ノーマル/n_わかりましたね？">
   <nature>interactive</nature>
   <permissions/>
  </behaviorContent>
  <behaviorContent path="ノーマル/n_オッス！">
   <nature>interactive</nature>
   <permissions/>
  </behaviorContent>
  <behaviorContent path="ノーマル/n_タブレットに注目">
   <nature>interactive</nature>
   <permissions/>
  </behaviorContent>
  <behaviorContent path="ノーマル/n_タブレットを読む">
   <nature>interactive</nature>
   <permissions/>
  </behaviorContent>
  <behaviorContent path="ノーマル/n_両手でしゅーりょー！">
   <nature>interactive</nature>
   <permissions/>
  </behaviorContent>
  <behaviorContent path="ノーマル/n_両手で煽りもっと">
   <nature>interactive</nature>
   <permissions/>
  </behaviorContent>
  <behaviorContent path="ノーマル/n_両手で胸おさえ">
   <nature>interactive</nature>
   <permissions/>
  </behaviorContent>
  <behaviorContent path="ノーマル/n_両手ひろげ">
   <nature>interactive</nature>
   <permissions/>
  </behaviorContent>
  <behaviorContent path="ノーマル/n_両手ひろげ後上げ下げなんてこった">
   <nature>interactive</nature>
   <permissions/>
  </behaviorContent>
  <behaviorContent path="ノーマル/n_両手ウッス腰へ">
   <nature>interactive</nature>
   <permissions/>
  </behaviorContent>
  <behaviorContent path="ノーマル/n_両手肩位置でバイバイ">
   <nature>interactive</nature>
   <permissions/>
  </behaviorContent>
  <behaviorContent path="ノーマル/n_口でカメラ撮影">
   <nature>interactive</nature>
   <permissions/>
  </behaviorContent>
  <behaviorContent path="ノーマル/n_右も左も">
   <nature>interactive</nature>
   <permissions/>
  </behaviorContent>
  <behaviorContent path="ノーマル/n_右側のみなさん">
   <nature>interactive</nature>
   <permissions/>
  </behaviorContent>
  <behaviorContent path="ノーマル/n_右向き手招き">
   <nature>interactive</nature>
   <permissions/>
  </behaviorContent>
  <behaviorContent path="ノーマル/n_右向き頼む">
   <nature>interactive</nature>
   <permissions/>
  </behaviorContent>
  <behaviorContent path="ノーマル/n_右手ひろげ">
   <nature>interactive</nature>
   <permissions/>
  </behaviorContent>
  <behaviorContent path="ノーマル/n_右手肩からバイバイロング">
   <nature>interactive</nature>
   <permissions/>
  </behaviorContent>
  <behaviorContent path="ノーマル/n_右手肩位置でバイバイ">
   <nature>interactive</nature>
   <permissions/>
  </behaviorContent>
  <behaviorContent path="ノーマル/n_基本姿勢">
   <nature>interactive</nature>
   <permissions/>
  </behaviorContent>
  <behaviorContent path="ノーマル/n_天を仰ぐ">
   <nature>interactive</nature>
   <permissions/>
  </behaviorContent>
  <behaviorContent path="ノーマル/n_左側のみなさん">
   <nature>interactive</nature>
   <permissions/>
  </behaviorContent>
  <behaviorContent path="ノーマル/n_左右どちら？">
   <nature>interactive</nature>
   <permissions/>
  </behaviorContent>
  <behaviorContent path="ノーマル/n_左手ひろげ">
   <nature>interactive</nature>
   <permissions/>
  </behaviorContent>
  <behaviorContent path="ノーマル/n_左手ひろげで、ですか？">
   <nature>interactive</nature>
   <permissions/>
  </behaviorContent>
  <behaviorContent path="ノーマル/n_店員さ～ん！">
   <nature>interactive</nature>
   <permissions/>
  </behaviorContent>
  <behaviorContent path="ノーマル/n_手をポン、そうか">
   <nature>interactive</nature>
   <permissions/>
  </behaviorContent>
  <behaviorContent path="ノーマル/n_手を交互に広げ">
   <nature>interactive</nature>
   <permissions/>
  </behaviorContent>
  <behaviorContent path="ノーマル/n_拍手">
   <nature>interactive</nature>
   <permissions/>
  </behaviorContent>
  <behaviorContent path="ノーマル/n_指を広げてこんなに沢山">
   <nature>interactive</nature>
   <permissions/>
  </behaviorContent>
  <behaviorContent path="ノーマル/n_歩く">
   <nature>interactive</nature>
   <permissions/>
  </behaviorContent>
  <behaviorContent path="ノーマル/n_片手でどうぞ">
   <nature>interactive</nature>
   <permissions/>
  </behaviorContent>
  <behaviorContent path="ノーマル/n_片手でタブレット注目">
   <nature>interactive</nature>
   <permissions/>
  </behaviorContent>
  <behaviorContent path="ノーマル/n_片手で胸をグっ">
   <nature>interactive</nature>
   <permissions/>
  </behaviorContent>
  <behaviorContent path="ノーマル/n_片手上げて見渡す">
   <nature>interactive</nature>
   <permissions/>
  </behaviorContent>
  <behaviorContent path="ノーマル/n_片手高く上げてバイバイ">
   <nature>interactive</nature>
   <permissions/>
  </behaviorContent>
  <behaviorContent path="ノーマル/n_眺める">
   <nature>interactive</nature>
   <permissions/>
  </behaviorContent>
  <behaviorContent path="ノーマル/n_胸に手(閉じて）">
   <nature>interactive</nature>
   <permissions/>
  </behaviorContent>
  <behaviorContent path="ノーマル/n_胸に手(開く）">
   <nature>interactive</nature>
   <permissions/>
  </behaviorContent>
  <behaviorContent path="ノーマル/n_見渡す">
   <nature>interactive</nature>
   <permissions/>
  </behaviorContent>
  <behaviorContent path="ノーマル/n_説得">
   <nature>interactive</nature>
   <permissions/>
  </behaviorContent>
  <behaviorContent path="ノーマル/n_顔さし">
   <nature>interactive</nature>
   <permissions/>
  </behaviorContent>
  <behaviorContent path="ポジティブ/+_いっくぞー！">
   <nature>interactive</nature>
   <permissions/>
  </behaviorContent>
  <behaviorContent path="ポジティブ/+_わくわく">
   <nature>interactive</nature>
   <permissions/>
  </behaviorContent>
  <behaviorContent path="ポジティブ/+_エクセレント！">
   <nature>interactive</nature>
   <permissions/>
  </behaviorContent>
  <behaviorContent path="ポジティブ/+_ドヤ">
   <nature>interactive</nature>
   <permissions/>
  </behaviorContent>
  <behaviorContent path="ポジティブ/+_バンザイ">
   <nature>interactive</nature>
   <permissions/>
  </behaviorContent>
  <behaviorContent path="ポジティブ/+_バンザイ2">
   <nature>interactive</nature>
   <permissions/>
  </behaviorContent>
  <behaviorContent path="ポジティブ/+_パーフェクト！">
   <nature>interactive</nature>
   <permissions/>
  </behaviorContent>
  <behaviorContent path="ポジティブ/+_上向きガッツ">
   <nature>interactive</nature>
   <permissions/>
  </behaviorContent>
  <behaviorContent path="ポジティブ/+_片手ずつバンザイ">
   <nature>interactive</nature>
   <permissions/>
  </behaviorContent>
  <behaviorContent path="ポジティブ/+_片手でガッツポーズ">
   <nature>interactive</nature>
   <permissions/>
  </behaviorContent>
  <behaviorContent path="ポジティブ/+_腕自慢">
   <nature>interactive</nature>
   <permissions/>
  </behaviorContent>
 </contents>
</package>
